Metadata-Version: 2.4
Name: pyThermoEst
Version: 0.2.1
Summary: A Python toolkit for estimating thermodynamic properties
Author-email: Sina Gilassi <sina.gilassi@gmail.com>
License-Expression: MIT
Project-URL: Homepage, https://github.com/sinagilassi/PyThermoEst
Project-URL: Documentation, https://pythermoest.readthedocs.io/en/latest/
Project-URL: Source, https://github.com/sinagilassi/PyThermoEst
Project-URL: Tracker, https://github.com/sinagilassi/PyThermoEst/issues
Keywords: chemical-engineering,thermodynamics,property-estimation,joback-method,zabransky-ruzicka-method,group-contribution-methods,parameter-estimation
Classifier: Development Status :: 1 - Planning
Classifier: Intended Audience :: Education
Classifier: Programming Language :: Python :: 3.11
Classifier: Operating System :: Unix
Classifier: Operating System :: MacOS :: MacOS X
Classifier: Operating System :: Microsoft :: Windows
Requires-Python: >=3.11
License-File: LICENSE
Requires-Dist: numpy>=2.3.5
Requires-Dist: scipy>=1.16.3
Requires-Dist: pandas>=2.3.3
Requires-Dist: pyyaml>=6.0.3
Requires-Dist: pydantic>=2.12.4
Requires-Dist: pydantic-settings>=2.12.0
Requires-Dist: pythermodb-settings
Requires-Dist: pycuc
Dynamic: license-file
